venvstacks-0.7.0.dist-info/METADATA
venvstacks-0.7.0.dist-info/WHEEL
venvstacks-0.7.0.dist-info/entry_points.txt
venvstacks-0.7.0.dist-info/licenses/LICENSE
venvstacks/__init__.py
venvstacks/__main__.py
venvstacks/_hash_content.py
venvstacks/_injected/README.md
venvstacks/_injected/postinstall.py
venvstacks/_source_tree.py
venvstacks/_ui/LICENSE
venvstacks/_ui/README.md
venvstacks/_ui/__init__.py
venvstacks/_ui/_types.py
venvstacks/_ui/render.py
venvstacks/_ui/termui.py
venvstacks/_util.py
venvstacks/cli.py
venvstacks/pack_venv.py
venvstacks/py.typed
venvstacks/stacks.py
venvstacks-0.7.0.dist-info/RECORD
