Metadata-Version: 2.1
Name: venvstacks
Version: 0.7.0
Summary: Use layered Python virtual environment stacks to share large dependencies
Keywords: packaging,dependency,venv
Author-Email: Alyssa Coghlan <ncoghlan@gmail.com>
Maintainer-Email: LM Studio <team@lmstudio.ai>
License: MIT
Classifier: Development Status :: 4 - Beta
Classifier: License :: OSI Approved :: MIT License
Classifier: Programming Language :: Python :: 3
Classifier: Programming Language :: Python :: 3.11
Classifier: Programming Language :: Python :: 3.12
Classifier: Programming Language :: Python :: 3.13
Classifier: Topic :: Software Development :: Build Tools
Classifier: Typing :: Typed
Project-URL: Homepage, https://github.com/lmstudio-ai/venvstacks
Project-URL: Documentation, https://venvstacks.lmstudio.ai/
Project-URL: Issues, https://github.com/lmstudio-ai/venvstacks/issues
Project-URL: Changelog, https://venvstacks.lmstudio.ai/changelog/
Requires-Python: >=3.11
Requires-Dist: pip>=24.1.1
Requires-Dist: pdm>=2.17.3
Requires-Dist: uv>=0.2.33
Requires-Dist: installer>=0.7.0
Requires-Dist: rich>=13.6.0
Requires-Dist: typer-slim>=0.12.4
Requires-Dist: tomlkit>=0.13.2
Requires-Dist: dulwich>=0.22.8
Provides-Extra: rich-cli
Requires-Dist: typer>=0.12.4; extra == "rich-cli"
